[{"pk": 1, "model": "products.categories", "fields": {"name": "sofa dog beds", "friendly_name": "Sofa Dog Beds"}}, {"pk": 2, "model": "products.categories", "fields": {"name": "bolster dog beds", "friendly_name": "Bolster Dog Beds"}}, {"pk": 3, "model": "products.categories", "fields": {"name": "hooded/dome dog beds", "friendly_name": "Hooded/Dome dog beds"}}, {"pk": 4, "model": "products.categories", "fields": {"name": "designer", "friendly_name": "Designer"}},{"pk": 5, "model": "products.categories", "fields": {"name": "deals", "friendly_name": "Deals"}}, {"pk": 6, "model": "products.categories", "fields": {"name": "new_arrivals", "friendly_name": "New Arrivals"}}]